odoo/addons/web_environment_ribbon/README.rst
odoo/addons/web_environment_ribbon/__init__.py
odoo/addons/web_environment_ribbon/__manifest__.py
odoo/addons/web_environment_ribbon/data/ribbon_data.xml
odoo/addons/web_environment_ribbon/i18n/ca.po
odoo/addons/web_environment_ribbon/i18n/de.po
odoo/addons/web_environment_ribbon/i18n/es.po
odoo/addons/web_environment_ribbon/i18n/fr.po
odoo/addons/web_environment_ribbon/i18n/hr.po
odoo/addons/web_environment_ribbon/i18n/it.po
odoo/addons/web_environment_ribbon/i18n/nl.po
odoo/addons/web_environment_ribbon/i18n/nl_NL.po
odoo/addons/web_environment_ribbon/i18n/pt.po
odoo/addons/web_environment_ribbon/i18n/pt_BR.po
odoo/addons/web_environment_ribbon/i18n/sl.po
odoo/addons/web_environment_ribbon/i18n/web_environment_ribbon.pot
odoo/addons/web_environment_ribbon/i18n/zh_CN.po
odoo/addons/web_environment_ribbon/models/__init__.py
odoo/addons/web_environment_ribbon/models/web_environment_ribbon_backend.py
odoo/addons/web_environment_ribbon/readme/CONFIGURE.rst
odoo/addons/web_environment_ribbon/readme/CONTRIBUTORS.rst
odoo/addons/web_environment_ribbon/readme/DESCRIPTION.rst
odoo/addons/web_environment_ribbon/readme/USAGE.rst
odoo/addons/web_environment_ribbon/static/description/icon.png
odoo/addons/web_environment_ribbon/static/description/index.html
odoo/addons/web_environment_ribbon/static/description/screenshot.png
odoo/addons/web_environment_ribbon/static/src/css/ribbon.css
odoo/addons/web_environment_ribbon/static/src/js/ribbon.js
odoo/addons/web_environment_ribbon/tests/__init__.py
odoo/addons/web_environment_ribbon/tests/test_environment_ribbon_data.py
odoo/addons/web_environment_ribbon/view/base_view.xml
odoo14_addon_web_environment_ribbon-14.0.1.0.1.dev11.dist-info/METADATA
odoo14_addon_web_environment_ribbon-14.0.1.0.1.dev11.dist-info/WHEEL
odoo14_addon_web_environment_ribbon-14.0.1.0.1.dev11.dist-info/top_level.txt
odoo14_addon_web_environment_ribbon-14.0.1.0.1.dev11.dist-info/RECORD
